MANIFEST.in
README.md
VERSION
requirements.txt
setup.py
rancher_upgrader/__init__.py
rancher_upgrader/rancher_upgrader.py
rancher_upgrader.egg-info/PKG-INFO
rancher_upgrader.egg-info/SOURCES.txt
rancher_upgrader.egg-info/dependency_links.txt
rancher_upgrader.egg-info/entry_points.txt
rancher_upgrader.egg-info/top_level.txt