Metadata-Version: 1.1
Name: rancher-upgrader
Version: 1.0.0
Summary: Small utility to upgrade Rancher Services
Home-page: UNKNOWN
Author: Daniel Garcia (cr0hn)
Author-email: cr0hn@cr0hn.com
License: UNKNOWN
Platform: UNKNOWN
Classifier: Environment :: Console
Classifier: Intended Audience :: System Administrators
Classifier: Intended Audience :: Other Audience
Classifier: License :: OSI Approved :: BSD License
Classifier: Operating System :: MacOS
Classifier: Operating System :: Microsoft :: Windows
Classifier: Operating System :: POSIX
Classifier: Programming Language :: Python :: 3.6
